odoo/addons/project_timeline_hr_timesheet/README.rst
odoo/addons/project_timeline_hr_timesheet/__init__.py
odoo/addons/project_timeline_hr_timesheet/__manifest__.py
odoo/addons/project_timeline_hr_timesheet/i18n/de.po
odoo/addons/project_timeline_hr_timesheet/i18n/project_timeline_hr_timesheet.pot
odoo/addons/project_timeline_hr_timesheet/readme/CONTRIBUTORS.rst
odoo/addons/project_timeline_hr_timesheet/readme/DESCRIPTION.rst
odoo/addons/project_timeline_hr_timesheet/static/description/icon.png
odoo/addons/project_timeline_hr_timesheet/static/description/index.html
odoo/addons/project_timeline_hr_timesheet/static/src/less/project_timeline_hr_timesheet.less
odoo/addons/project_timeline_hr_timesheet/templates/assets.xml
odoo/addons/project_timeline_hr_timesheet/views/project_task_view.xml
odoo11_addon_project_timeline_hr_timesheet-11.0.1.0.0.99.dev7.dist-info/METADATA
odoo11_addon_project_timeline_hr_timesheet-11.0.1.0.0.99.dev7.dist-info/WHEEL
odoo11_addon_project_timeline_hr_timesheet-11.0.1.0.0.99.dev7.dist-info/top_level.txt
odoo11_addon_project_timeline_hr_timesheet-11.0.1.0.0.99.dev7.dist-info/RECORD
